office/__init__.py
office/email.py
office/excel.py
office/file.py
office/image.py
office/ocr.py
office/pdf.py
office/ppt.py
office/tools.py
office/video.py
office/web.py
office/word.py
service/__init__.py
service/image/__init__.py
service/image/add_watermark_service.py
service/pdf/__init__.py
service/pdf/add_watermark_service.py
service/ppt/__init__.py
service/ppt/ppt2pdf_service.py
utils/__init__.py
utils/pandas_mem.py
utils/progress.py
python_office_deepin-0.0.1.dist-info/LICENSE
python_office_deepin-0.0.1.dist-info/METADATA
python_office_deepin-0.0.1.dist-info/WHEEL
python_office_deepin-0.0.1.dist-info/top_level.txt
python_office_deepin-0.0.1.dist-info/RECORD
