Metadata-Version: 2.1
Name: python-office-deepin
Version: 0.0.1
Summary: python for office
Home-page: https://github.com/CoderWanFeng/python-office
Author: CoderWanFeng
Author-email: 1957875073@qq.com
License: Apache-2.0 license
Project-URL: Bug Tracker, https://github.com/CoderWanFeng/python-office/issues
Project-URL: Documentation, https://github.com/CoderWanFeng/python-office/blob/master/README.md
Project-URL: Source Code, https://github.com/CoderWanFeng/python-office
Platform: any
Requires-Python: >=3.6
License-File: LICENSE
Requires-Dist: xlrd
Requires-Dist: xlwt
Requires-Dist: xlutils
Requires-Dist: xlwings
Requires-Dist: python-docx
Requires-Dist: python-pptx
Requires-Dist: PyPDF2
Requires-Dist: easyocr
Requires-Dist: openpyxl
Requires-Dist: pandas
Requires-Dist: Faker
Requires-Dist: reportlab
Requires-Dist: rich (>=9.13.0)
Requires-Dist: moviepy
Requires-Dist: fpdf
Requires-Dist: qrcode
Requires-Dist: translate
Requires-Dist: pikepdf
Requires-Dist: pypiwin32
Requires-Dist: progress
Requires-Dist: alive-progress
Requires-Dist: pdf2docx
